ipython_bg/__init__.py
ipython_bg-0.2.dist-info/LICENSE
ipython_bg-0.2.dist-info/METADATA
ipython_bg-0.2.dist-info/WHEEL
ipython_bg-0.2.dist-info/top_level.txt
ipython_bg-0.2.dist-info/RECORD
