Metadata-Version: 2.1
Name: ipython-bg
Version: 0.2
Summary: IPython magic to run jobs in background
Home-page: http://www.github.com/drorspei/ipython-bg
Author: Dror Speiser
License: MIT
Keywords: ipython bg jobs
Platform: UNKNOWN
Classifier: Development Status :: 3 - Alpha
Classifier: Intended Audience :: Developers
Classifier: Framework :: IPython
Classifier: Programming Language :: Python
Classifier: Topic :: Utilities
Requires-Dist: ipython
